<?xml version="1.0"?>
<root>
  <name>sds</name>
  <longname>SDS File</longname>
  <title>SDS File</title>
  <filterspec>SDS*</filterspec>
  <callback>muppet_addDatasetQP</callback>
  <option>
    <name>filetype</name>
  </option>
  <option>
    <name>filename</name>
  </option>
  <option>
    <name>domain</name>
  </option>
  <option>
    <name>parameter</name>
  </option>
  <option>
    <name>subfield</name>
  </option>
  <option>
    <name>plotcoordinate</name>
  </option>
  <option>
    <name>component</name>
  </option>
  <option>
    <name>timestep</name>
  </option>
  <option>
    <name>time</name>
  </option>
  <option>
    <name>station</name>
  </option>
  <option>
    <name>m</name>
  </option>
  <option>
    <name>n</name>
  </option>
  <option>
    <name>k</name>
  </option>
</root>
